ImageObject.cp311-win_amd64.pyd
ImageObject_Flood-1.0.1.dist-info/METADATA
ImageObject_Flood-1.0.1.dist-info/WHEEL
ImageObject_Flood-1.0.1.dist-info/top_level.txt
ImageObject_Flood-1.0.1.dist-info/RECORD
